{
    "sourceFile": "frontend/actions/song/getSuggestion.ts",
    "activeCommit": 0,
    "commits": [
        {
            "activePatchIndex": 9,
            "patches": [
                {
                    "date": 1717454296568,
                    "content": "Index: \n===================================================================\n--- \n+++ \n"
                },
                {
                    "date": 1717454301730,
                    "content": "Index: \n===================================================================\n--- \n+++ \n@@ -2,9 +2,9 @@\n import Library from \"@/components/Library\";\r\n import { LibraryType } from \"@/const/libraryType\";\r\n import { Song } from \"@/scheme/Song\";\r\n \r\n-const getSongByUserId = async (id: string): Promise<Song[] | null> => {\r\n+const getSu = async (id: string): Promise<Song[] | null> => {\r\n   try {\r\n     const { data } = await axiosClient.get(`/song/get/user/${id}`);\r\n     const res = data.map((song: any) => {\r\n       song.id = song._id;\r\n"
                },
                {
                    "date": 1717454311862,
                    "content": "Index: \n===================================================================\n--- \n+++ \n@@ -2,9 +2,9 @@\n import Library from \"@/components/Library\";\r\n import { LibraryType } from \"@/const/libraryType\";\r\n import { Song } from \"@/scheme/Song\";\r\n \r\n-const getSu = async (id: string): Promise<Song[] | null> => {\r\n+const getSuggestion = async (id: string): Promise<Song[] | null> => {\r\n   try {\r\n     const { data } = await axiosClient.get(`/song/get/user/${id}`);\r\n     const res = data.map((song: any) => {\r\n       song.id = song._id;\r\n@@ -18,5 +18,5 @@\n     return null;\r\n   }\r\n };\r\n \r\n-export default getSongByUserId;\r\n+export default getSuggestion;\r\n"
                },
                {
                    "date": 1717454384407,
                    "content": "Index: \n===================================================================\n--- \n+++ \n@@ -2,11 +2,11 @@\n import Library from \"@/components/Library\";\r\n import { LibraryType } from \"@/const/libraryType\";\r\n import { Song } from \"@/scheme/Song\";\r\n \r\n-const getSuggestion = async (id: string): Promise<Song[] | null> => {\r\n+const getSuggestion = async (id: string) => {\r\n   try {\r\n-    const { data } = await axiosClient.get(`/song/get/user/${id}`);\r\n+    const { data } = await axiosClient.get(`/song/sug/user/${id}`);\r\n     const res = data.map((song: any) => {\r\n       song.id = song._id;\r\n       song.type = LibraryType.Song;\r\n       delete song._id;\r\n"
                },
                {
                    "date": 1717454396243,
                    "content": "Index: \n===================================================================\n--- \n+++ \n@@ -0,0 +1,16 @@\n+import axiosClient from \"@/app/_utils/GlobalApi\";\r\n+import Library from \"@/components/Library\";\r\n+import { LibraryType } from \"@/const/libraryType\";\r\n+import { Song } from \"@/scheme/Song\";\r\n+\r\n+const getSuggestion = async (id: string) => {\r\n+  try {\r\n+    const { data } = await axiosClient.get(`/song/suggestion/${id}`);\r\n+    return res || [];\r\n+  } catch (error) {\r\n+    console.log(error);\r\n+    return null;\r\n+  }\r\n+};\r\n+\r\n+export default getSuggestion;\r\n"
                },
                {
                    "date": 1717454405929,
                    "content": "Index: \n===================================================================\n--- \n+++ \n@@ -0,0 +1,16 @@\n+import axiosClient from \"@/app/_utils/GlobalApi\";\r\n+import Library from \"@/components/Library\";\r\n+import { LibraryType } from \"@/const/libraryType\";\r\n+import { Song } from \"@/scheme/Song\";\r\n+\r\n+const getSuggestion = async (id: string) => {\r\n+  try {\r\n+    const { data } = await axiosClient.get(`/song/suggestion/${id}`);\r\n+    return data || {};\r\n+  } catch (error) {\r\n+    console.log(error);\r\n+    return null;\r\n+  }\r\n+};\r\n+\r\n+export default getSuggestion;\r\n"
                },
                {
                    "date": 1717454411139,
                    "content": "Index: \n===================================================================\n--- \n+++ \n@@ -1,8 +1,5 @@\n import axiosClient from \"@/app/_utils/GlobalApi\";\r\n-import Library from \"@/components/Library\";\r\n-import { LibraryType } from \"@/const/libraryType\";\r\n-import { Song } from \"@/scheme/Song\";\r\n \r\n const getSuggestion = async (id: string) => {\r\n   try {\r\n     const { data } = await axiosClient.get(`/song/suggestion/${id}`);\r\n@@ -13,42 +10,4 @@\n   }\r\n };\r\n \r\n export default getSuggestion;\r\n-import axiosClient from \"@/app/_utils/GlobalApi\";\r\n-import Library from \"@/components/Library\";\r\n-import { LibraryType } from \"@/const/libraryType\";\r\n-import { Song } from \"@/scheme/Song\";\r\n-\r\n-const getSuggestion = async (id: string) => {\r\n-  try {\r\n-    const { data } = await axiosClient.get(`/song/suggestion/${id}`);\r\n-    return res || [];\r\n-  } catch (error) {\r\n-    console.log(error);\r\n-    return null;\r\n-  }\r\n-};\r\n-\r\n-export default getSuggestion;\r\n-import axiosClient from \"@/app/_utils/GlobalApi\";\r\n-import Library from \"@/components/Library\";\r\n-import { LibraryType } from \"@/const/libraryType\";\r\n-import { Song } from \"@/scheme/Song\";\r\n-\r\n-const getSuggestion = async (id: string) => {\r\n-  try {\r\n-    const { data } = await axiosClient.get(`/song/sug/user/${id}`);\r\n-    const res = data.map((song: any) => {\r\n-      song.id = song._id;\r\n-      song.type = LibraryType.Song;\r\n-      delete song._id;\r\n-      return song;\r\n-    });\r\n-    return res || [];\r\n-  } catch (error) {\r\n-    console.log(error);\r\n-    return null;\r\n-  }\r\n-};\r\n-\r\n-export default getSuggestion;\r\n"
                },
                {
                    "date": 1717459625704,
                    "content": "Index: \n===================================================================\n--- \n+++ \n@@ -2,8 +2,9 @@\n \r\n const getSuggestion = async (id: string) => {\r\n   try {\r\n     const { data } = await axiosClient.get(`/song/suggestion/${id}`);\r\n+    da\r\n     return data || {};\r\n   } catch (error) {\r\n     console.log(error);\r\n     return null;\r\n"
                },
                {
                    "date": 1717459633125,
                    "content": "Index: \n===================================================================\n--- \n+++ \n@@ -3,8 +3,9 @@\n const getSuggestion = async (id: string) => {\r\n   try {\r\n     const { data } = await axiosClient.get(`/song/suggestion/${id}`);\r\n     data.tracks = data.tracks?.map((song: any) => {\r\n+        \r\n     return data || {};\r\n   } catch (error) {\r\n     console.log(error);\r\n     return null;\r\n"
                },
                {
                    "date": 1717459647027,
                    "content": "Index: \n===================================================================\n--- \n+++ \n@@ -3,9 +3,14 @@\n const getSuggestion = async (id: string) => {\r\n   try {\r\n     const { data } = await axiosClient.get(`/song/suggestion/${id}`);\r\n     data.tracks = data.tracks?.map((song: any) => {\r\n-        \r\n+        song.id = song._id;\r\n+        delete song._id;\r\n+        return song;\r\n+        }\r\n+    );\r\n+    data.\r\n     return data || {};\r\n   } catch (error) {\r\n     console.log(error);\r\n     return null;\r\n"
                }
            ],
            "date": 1717454296568,
            "name": "Commit-0",
            "content": "import axiosClient from \"@/app/_utils/GlobalApi\";\r\nimport Library from \"@/components/Library\";\r\nimport { LibraryType } from \"@/const/libraryType\";\r\nimport { Song } from \"@/scheme/Song\";\r\n\r\nconst getSongByUserId = async (id: string): Promise<Song[] | null> => {\r\n  try {\r\n    const { data } = await axiosClient.get(`/song/get/user/${id}`);\r\n    const res = data.map((song: any) => {\r\n      song.id = song._id;\r\n      song.type = LibraryType.Song;\r\n      delete song._id;\r\n      return song;\r\n    });\r\n    return res || [];\r\n  } catch (error) {\r\n    console.log(error);\r\n    return null;\r\n  }\r\n};\r\n\r\nexport default getSongByUserId;\r\n"
        }
    ]
}