{
    "sourceFile": "frontend/app/liked/page.tsx",
    "activeCommit": 0,
    "commits": [
        {
            "activePatchIndex": 6,
            "patches": [
                {
                    "date": 1717456879296,
                    "content": "Index: \n===================================================================\n--- \n+++ \n"
                },
                {
                    "date": 1717456885553,
                    "content": "Index: \n===================================================================\n--- \n+++ \n@@ -2,14 +2,15 @@\n import Header from '@/components/Header';\r\n import Image from 'next/image';\r\n import React from 'react';\r\n import LikedContent from './components/LikedContent';\r\n+import getLikedSongs from '@/actions/song/getLikedSongs';\r\n \r\n export const revalidate = 0;\r\n \r\n const Liked = async () => {\r\n   //add song:\r\n-  const songs = await ... liked\r\n+  const songs = await getLikedSongs('1');\r\n   const songs = fakeGetSong();\r\n   return (\r\n     <div className=\"bg-neutral-900 rounded-lg h-full w-full overflow-hidden overflow-y-auto\">\r\n       <Header>\r\n"
                },
                {
                    "date": 1717456891967,
                    "content": "Index: \n===================================================================\n--- \n+++ \n@@ -0,0 +1,40 @@\n+import fakeGetSong from '@/actions/api/getSong';\r\n+import Header from '@/components/Header';\r\n+import Image from 'next/image';\r\n+import React from 'react';\r\n+import LikedContent from './components/LikedContent';\r\n+import getLikedSongs from '@/actions/song/getLikedSongs';\r\n+\r\n+export const revalidate = 0;\r\n+\r\n+const Liked = async () => {\r\n+  //add song:\r\n+  const songs = await getLikedSongs();\r\n+  return (\r\n+    <div className=\"bg-neutral-900 rounded-lg h-full w-full overflow-hidden overflow-y-auto\">\r\n+      <Header>\r\n+        <div className=\"mt-20\">\r\n+          <div className=\"flex flex-col md:flex-row items-center gap-x-5\">\r\n+            <div className=\"relative h-32 w-32 lg:h-44 lg:w-44\">\r\n+              <Image\r\n+                fill\r\n+                src=\"/images/liked.png\"\r\n+                alt=\"Playlist\"\r\n+                className=\"object-cover\"\r\n+              />\r\n+            </div>\r\n+            <div className=\"flex flex-col gap-y-2 mt-4 md:mt-0\">\r\n+              <p className=\"hidden md:block font-semibold text-sm\">Playlist</p>\r\n+              <h1 className=\"text-white text-4xl sm:text-5xl lg:text-7xl font-bold\">\r\n+                Liked Songs\r\n+              </h1>\r\n+            </div>\r\n+          </div>\r\n+        </div>\r\n+      </Header>\r\n+      <LikedContent songs={songs} />\r\n+    </div>\r\n+  );\r\n+};\r\n+\r\n+export default Liked;\r\n"
                },
                {
                    "date": 1717456900530,
                    "content": "Index: \n===================================================================\n--- \n+++ \n@@ -1,5 +1,5 @@\n-import fakeGetSong from '@/actions/api/getSong';\r\n+\r\n import Header from '@/components/Header';\r\n import Image from 'next/image';\r\n import React from 'react';\r\n import LikedContent from './components/LikedContent';\r\n"
                },
                {
                    "date": 1717456906694,
                    "content": "Index: \n===================================================================\n--- \n+++ \n@@ -1,4 +1,5 @@\n+'use client'\r\n \r\n import Header from '@/components/Header';\r\n import Image from 'next/image';\r\n import React from 'react';\r\n@@ -37,45 +38,4 @@\n   );\r\n };\r\n \r\n export default Liked;\r\n-import fakeGetSong from '@/actions/api/getSong';\r\n-import Header from '@/components/Header';\r\n-import Image from 'next/image';\r\n-import React from 'react';\r\n-import LikedContent from './components/LikedContent';\r\n-import getLikedSongs from '@/actions/song/getLikedSongs';\r\n-\r\n-export const revalidate = 0;\r\n-\r\n-const Liked = async () => {\r\n-  //add song:\r\n-  const songs = await getLikedSongs('1');\r\n-  const songs = fakeGetSong();\r\n-  return (\r\n-    <div className=\"bg-neutral-900 rounded-lg h-full w-full overflow-hidden overflow-y-auto\">\r\n-      <Header>\r\n-        <div className=\"mt-20\">\r\n-          <div className=\"flex flex-col md:flex-row items-center gap-x-5\">\r\n-            <div className=\"relative h-32 w-32 lg:h-44 lg:w-44\">\r\n-              <Image\r\n-                fill\r\n-                src=\"/images/liked.png\"\r\n-                alt=\"Playlist\"\r\n-                className=\"object-cover\"\r\n-              />\r\n-            </div>\r\n-            <div className=\"flex flex-col gap-y-2 mt-4 md:mt-0\">\r\n-              <p className=\"hidden md:block font-semibold text-sm\">Playlist</p>\r\n-              <h1 className=\"text-white text-4xl sm:text-5xl lg:text-7xl font-bold\">\r\n-                Liked Songs\r\n-              </h1>\r\n-            </div>\r\n-          </div>\r\n-        </div>\r\n-      </Header>\r\n-      <LikedContent songs={songs} />\r\n-    </div>\r\n-  );\r\n-};\r\n-\r\n-export default Liked;\r\n"
                },
                {
                    "date": 1717456924025,
                    "content": "Index: \n===================================================================\n--- \n+++ \n@@ -8,9 +8,9 @@\n \r\n export const revalidate = 0;\r\n \r\n const Liked = () => {\r\n-  //add song:\r\n+  const {data: session} = useSession();\r\n   const songs = await getLikedSongs();\r\n   return (\r\n     <div className=\"bg-neutral-900 rounded-lg h-full w-full overflow-hidden overflow-y-auto\">\r\n       <Header>\r\n"
                },
                {
                    "date": 1717456991634,
                    "content": "Index: \n===================================================================\n--- \n+++ \n@@ -0,0 +1,49 @@\n+'use client';\r\n+\r\n+import Header from '@/components/Header';\r\n+import Image from 'next/image';\r\n+import React from 'react';\r\n+import LikedContent from './components/LikedContent';\r\n+import getLikedSongs from '@/actions/song/getLikedSongs';\r\n+\r\n+\r\n+const Liked = () => {\r\n+  const { data: session } = useSession();\r\n+  const [songs, setSongs] = useState([]);\r\n+\r\n+  useEffect(() => {\r\n+    const fetchSongs = async () => {\r\n+      const songsData = await getLikedSongs();\r\n+      setSongs(songsData);\r\n+    };\r\n+\r\n+    fetchSongs();\r\n+  }, []);\r\n+  return (\r\n+    <div className=\"bg-neutral-900 rounded-lg h-full w-full overflow-hidden overflow-y-auto\">\r\n+      <Header>\r\n+        <div className=\"mt-20\">\r\n+          <div className=\"flex flex-col md:flex-row items-center gap-x-5\">\r\n+            <div className=\"relative h-32 w-32 lg:h-44 lg:w-44\">\r\n+              <Image\r\n+                fill\r\n+                src=\"/images/liked.png\"\r\n+                alt=\"Playlist\"\r\n+                className=\"object-cover\"\r\n+              />\r\n+            </div>\r\n+            <div className=\"flex flex-col gap-y-2 mt-4 md:mt-0\">\r\n+              <p className=\"hidden md:block font-semibold text-sm\">Playlist</p>\r\n+              <h1 className=\"text-white text-4xl sm:text-5xl lg:text-7xl font-bold\">\r\n+                Liked Songs\r\n+              </h1>\r\n+            </div>\r\n+          </div>\r\n+        </div>\r\n+      </Header>\r\n+      <LikedContent songs={songs} />\r\n+    </div>\r\n+  );\r\n+};\r\n+\r\n+export default Liked;\r\n"
                }
            ],
            "date": 1717456879296,
            "name": "Commit-0",
            "content": "import fakeGetSong from '@/actions/api/getSong';\r\nimport Header from '@/components/Header';\r\nimport Image from 'next/image';\r\nimport React from 'react';\r\nimport LikedContent from './components/LikedContent';\r\n\r\nexport const revalidate = 0;\r\n\r\nconst Liked = async () => {\r\n  //add song:\r\n  const songs = await ... liked\r\n  const songs = fakeGetSong();\r\n  return (\r\n    <div className=\"bg-neutral-900 rounded-lg h-full w-full overflow-hidden overflow-y-auto\">\r\n      <Header>\r\n        <div className=\"mt-20\">\r\n          <div className=\"flex flex-col md:flex-row items-center gap-x-5\">\r\n            <div className=\"relative h-32 w-32 lg:h-44 lg:w-44\">\r\n              <Image\r\n                fill\r\n                src=\"/images/liked.png\"\r\n                alt=\"Playlist\"\r\n                className=\"object-cover\"\r\n              />\r\n            </div>\r\n            <div className=\"flex flex-col gap-y-2 mt-4 md:mt-0\">\r\n              <p className=\"hidden md:block font-semibold text-sm\">Playlist</p>\r\n              <h1 className=\"text-white text-4xl sm:text-5xl lg:text-7xl font-bold\">\r\n                Liked Songs\r\n              </h1>\r\n            </div>\r\n          </div>\r\n        </div>\r\n      </Header>\r\n      <LikedContent songs={songs} />\r\n    </div>\r\n  );\r\n};\r\n\r\nexport default Liked;\r\n"
        }
    ]
}